README.rst
setup.py
heka_py_raven.egg-info/PKG-INFO
heka_py_raven.egg-info/SOURCES.txt
heka_py_raven.egg-info/dependency_links.txt
heka_py_raven.egg-info/not-zip-safe
heka_py_raven.egg-info/requires.txt
heka_py_raven.egg-info/top_level.txt
heka_raven/__init__.py
heka_raven/raven_plugin.py