Metadata-Version: 1.1
Name: heka-py-raven
Version: 0.7
Summary: A heka-py plugin to send exceptions to Sentry
Home-page: http://github.com/mozilla-services/heka-py-raven
Author: Victor Ng
Author-email: vng@mozilla.com
License: MPLv2.0
Platform: UNKNOWN
Classifier: License :: OSI Approved :: Mozilla Public License 2.0 (MPL 2.0)
